accelbyte_py_sdk/api/platform/__init__.py
accelbyte_py_sdk/api/platform/errors.py
accelbyte_py_sdk/api/platform/models/__init__.py
accelbyte_py_sdk/api/platform/models/achievement_info.py
accelbyte_py_sdk/api/platform/models/action.py
accelbyte_py_sdk/api/platform/models/action_request.py
accelbyte_py_sdk/api/platform/models/additional_data.py
accelbyte_py_sdk/api/platform/models/additional_data_entitlement.py
accelbyte_py_sdk/api/platform/models/admin_entitlement_decrement.py
accelbyte_py_sdk/api/platform/models/admin_entitlement_sold_request.py
accelbyte_py_sdk/api/platform/models/admin_order_create.py
accelbyte_py_sdk/api/platform/models/adyen_config.py
accelbyte_py_sdk/api/platform/models/ali_pay_config.py
accelbyte_py_sdk/api/platform/models/app_config.py
accelbyte_py_sdk/api/platform/models/app_entitlement_info.py
accelbyte_py_sdk/api/platform/models/app_entitlement_paging_sliced_result.py
accelbyte_py_sdk/api/platform/models/app_info.py
accelbyte_py_sdk/api/platform/models/app_localization.py
accelbyte_py_sdk/api/platform/models/app_update.py
accelbyte_py_sdk/api/platform/models/apple_iap_config_info.py
accelbyte_py_sdk/api/platform/models/apple_iap_config_request.py
accelbyte_py_sdk/api/platform/models/apple_iap_config_version_info.py
accelbyte_py_sdk/api/platform/models/apple_iap_receipt.py
accelbyte_py_sdk/api/platform/models/apple_iap_request.py
accelbyte_py_sdk/api/platform/models/available_comparison.py
accelbyte_py_sdk/api/platform/models/available_predicate.py
accelbyte_py_sdk/api/platform/models/available_price.py
accelbyte_py_sdk/api/platform/models/base_custom_config.py
accelbyte_py_sdk/api/platform/models/base_tls_config.py
accelbyte_py_sdk/api/platform/models/basic_category_info.py
accelbyte_py_sdk/api/platform/models/basic_item.py
accelbyte_py_sdk/api/platform/models/billing_account.py
accelbyte_py_sdk/api/platform/models/billing_history_info.py
accelbyte_py_sdk/api/platform/models/billing_history_paging_sliced_result.py
accelbyte_py_sdk_service_platform-0.26.0.dist-info/METADATA
accelbyte_py_sdk_service_platform-0.26.0.dist-info/WHEEL
accelbyte_py_sdk_service_platform-0.26.0.dist-info/top_level.txt
accelbyte_py_sdk_service_platform-0.26.0.dist-info/RECORD
